odoo8_addon_sale_partner_order_policy-8.0.1.0.0.99.dev24-py3.8-nspkg.pth
odoo_addons/sale_partner_order_policy/__init__.py
odoo_addons/sale_partner_order_policy/__openerp__.py
odoo_addons/sale_partner_order_policy/partner.py
odoo_addons/sale_partner_order_policy/partner_demo.xml
odoo_addons/sale_partner_order_policy/partner_view.xml
odoo_addons/sale_partner_order_policy/sale.py
odoo_addons/sale_partner_order_policy/i18n/am.po
odoo_addons/sale_partner_order_policy/i18n/ar.po
odoo_addons/sale_partner_order_policy/i18n/bg.po
odoo_addons/sale_partner_order_policy/i18n/bs.po
odoo_addons/sale_partner_order_policy/i18n/ca.po
odoo_addons/sale_partner_order_policy/i18n/cs.po
odoo_addons/sale_partner_order_policy/i18n/da.po
odoo_addons/sale_partner_order_policy/i18n/de.po
odoo_addons/sale_partner_order_policy/i18n/el_GR.po
odoo_addons/sale_partner_order_policy/i18n/en_GB.po
odoo_addons/sale_partner_order_policy/i18n/es.po
odoo_addons/sale_partner_order_policy/i18n/es_CR.po
odoo_addons/sale_partner_order_policy/i18n/es_EC.po
odoo_addons/sale_partner_order_policy/i18n/es_ES.po
odoo_addons/sale_partner_order_policy/i18n/es_MX.po
odoo_addons/sale_partner_order_policy/i18n/es_VE.po
odoo_addons/sale_partner_order_policy/i18n/et.po
odoo_addons/sale_partner_order_policy/i18n/fi.po
odoo_addons/sale_partner_order_policy/i18n/fr.po
odoo_addons/sale_partner_order_policy/i18n/fr_CH.po
odoo_addons/sale_partner_order_policy/i18n/gl.po
odoo_addons/sale_partner_order_policy/i18n/hr.po
odoo_addons/sale_partner_order_policy/i18n/hr_HR.po
odoo_addons/sale_partner_order_policy/i18n/hu.po
odoo_addons/sale_partner_order_policy/i18n/id.po
odoo_addons/sale_partner_order_policy/i18n/it.po
odoo_addons/sale_partner_order_policy/i18n/ja.po
odoo_addons/sale_partner_order_policy/i18n/lt.po
odoo_addons/sale_partner_order_policy/i18n/lv.po
odoo_addons/sale_partner_order_policy/i18n/mk.po
odoo_addons/sale_partner_order_policy/i18n/mn.po
odoo_addons/sale_partner_order_policy/i18n/nb.po
odoo8_addon_sale_partner_order_policy-8.0.1.0.0.99.dev24.dist-info/METADATA
odoo8_addon_sale_partner_order_policy-8.0.1.0.0.99.dev24.dist-info/WHEEL
odoo8_addon_sale_partner_order_policy-8.0.1.0.0.99.dev24.dist-info/namespace_packages.txt
odoo8_addon_sale_partner_order_policy-8.0.1.0.0.99.dev24.dist-info/top_level.txt
odoo8_addon_sale_partner_order_policy-8.0.1.0.0.99.dev24.dist-info/RECORD
